MANIFEST.in
setup.cfg
setup.py
tenyksclient/__init__.py
tenyksclient/client.py
tenyksclient/config.py
tenyksclient/module_loader.py
tenyksclient/settings.py.dist
tenyksclient.egg-info/PKG-INFO
tenyksclient.egg-info/SOURCES.txt
tenyksclient.egg-info/dependency_links.txt
tenyksclient.egg-info/entry_points.txt
tenyksclient.egg-info/not-zip-safe
tenyksclient.egg-info/requires.txt
tenyksclient.egg-info/top_level.txt