Metadata-Version: 1.0
Name: tenyksclient
Version: 0.1.23
Summary: A client base for Tenyks IRC bot
Home-page: https://github.com/kyleterry/tenyksclient
Author: Kyle Terry
Author-email: kyle@kyleterry.com
License: https://raw.github.com/kyleterry/tenyksclient/master/LICENSE
Keywords: ircbot baseclient tenyks
Platform: UNKNOWN
